ehrdata/__init__.py
ehrdata/_compat.py
ehrdata/_feature_types.py
ehrdata/_logger.py
ehrdata/_types.py
ehrdata/core/__init__.py
ehrdata/core/constants.py
ehrdata/core/ehrdata.py
ehrdata/core/index.py
ehrdata/dt/__init__.py
ehrdata/dt/_dataloader.py
ehrdata/dt/datasets.py
ehrdata/integrations/__init__.py
ehrdata/integrations/torch/__init__.py
ehrdata/integrations/torch/_dataset.py
ehrdata/integrations/vitessce/__init__.py
ehrdata/integrations/vitessce/_config.py
ehrdata/io/__init__.py
ehrdata/io/_array_casting.py
ehrdata/io/_omop_utils.py
ehrdata/io/csv.py
ehrdata/io/h5ad.py
ehrdata/io/pandas.py
ehrdata/io/zarr.py
ehrdata/io/omop/__init__.py
ehrdata/io/omop/_check_arguments.py
ehrdata/io/omop/_queries.py
ehrdata/io/omop/omop.py
ehrdata-0.0.10.dist-info/METADATA
ehrdata-0.0.10.dist-info/WHEEL
ehrdata-0.0.10.dist-info/licenses/LICENSE
ehrdata-0.0.10.dist-info/RECORD
