Metadata-Version: 2.4
Name: ehrdata
Version: 0.0.10
Summary: A Python package for EHR data
Project-URL: Documentation, https://ehrdata.readthedocs.io/
Project-URL: Homepage, https://github.com/theislab/ehrdata
Project-URL: Source, https://github.com/theislab/ehrdata
Author: Eljas Roellin, Lukas Heumos, Xinyue Zhang
Maintainer-email: Eljas Roellin <eljas.roellin@helmholtz-munich.de>, Lukas Heumos <lukas.heumos@posteo.net>
License-Expression: Apache-2.0
License-File: LICENSE
Classifier: Programming Language :: Python :: 3 :: Only
Classifier: Programming Language :: Python :: 3.12
Classifier: Programming Language :: Python :: 3.13
Requires-Python: <3.14,>=3.12
Requires-Dist: anndata>=0.11
Requires-Dist: duckdb
Requires-Dist: fast-array-utils[sparse]
Requires-Dist: filelock
Requires-Dist: requests
Requires-Dist: rich
Requires-Dist: xarray
Requires-Dist: zarr>=3
Provides-Extra: dask
Requires-Dist: dask; extra == 'dask'
Provides-Extra: dev
Requires-Dist: pre-commit; extra == 'dev'
Requires-Dist: twine; extra == 'dev'
Provides-Extra: doc
Requires-Dist: docutils!=0.18.*,!=0.19.*,>=0.8; extra == 'doc'
Requires-Dist: ipykernel; extra == 'doc'
Requires-Dist: ipython; extra == 'doc'
Requires-Dist: lamindb>=1.1; extra == 'doc'
Requires-Dist: myst-nb>=1.1; extra == 'doc'
Requires-Dist: pandas; extra == 'doc'
Requires-Dist: scanpydoc; extra == 'doc'
Requires-Dist: sphinx-autodoc-typehints; extra == 'doc'
Requires-Dist: sphinx-book-theme>=1; extra == 'doc'
Requires-Dist: sphinx-copybutton; extra == 'doc'
Requires-Dist: sphinx-tabs; extra == 'doc'
Requires-Dist: sphinx>=4; extra == 'doc'
Requires-Dist: sphinxcontrib-bibtex>=1; extra == 'doc'
Requires-Dist: sphinxext-opengraph; extra == 'doc'
Requires-Dist: torch; extra == 'doc'
Requires-Dist: vitessce; extra == 'doc'
Provides-Extra: ehrapy
Requires-Dist: ehrapy; extra == 'ehrapy'
Provides-Extra: lamin
Requires-Dist: lamindb>=1.1; extra == 'lamin'
Provides-Extra: test
Requires-Dist: coverage; extra == 'test'
Requires-Dist: dask; extra == 'test'
Requires-Dist: lamindb>=1.1; extra == 'test'
Requires-Dist: pytest; extra == 'test'
Requires-Dist: pytest-cov; extra == 'test'
Requires-Dist: torch; extra == 'test'
Requires-Dist: vitessce[all]>=3.4; extra == 'test'
Provides-Extra: torch
Requires-Dist: torch; extra == 'torch'
Provides-Extra: vitessce
Requires-Dist: vitessce[all]>=3.4; extra == 'vitessce'
